setup.py
routeplot/__init__.py
routeplot/routeplot.py
routeplot.egg-info/PKG-INFO
routeplot.egg-info/SOURCES.txt
routeplot.egg-info/dependency_links.txt
routeplot.egg-info/not-zip-safe
routeplot.egg-info/top_level.txt