Metadata-Version: 1.0
Name: routeplot
Version: 0.1
Summary: Creates an HTML file which contains the map data
Home-page: https://github.com/Vijaysai005/MyPythonFiles/
Author: Vijayasai S
Author-email: vijay.sai005@gmail.com
License: GNU General Public Licencse
Platform: UNKNOWN
